KNearestNeighborSampling/KNNSampler.py
KNearestNeighborSampling/__init__.py
KNearestNeighborSampling-0.0.2.dist-info/LICENSE
KNearestNeighborSampling-0.0.2.dist-info/METADATA
KNearestNeighborSampling-0.0.2.dist-info/WHEEL
KNearestNeighborSampling-0.0.2.dist-info/top_level.txt
KNearestNeighborSampling-0.0.2.dist-info/RECORD
