Metadata-Version: 2.1
Name: KNearestNeighborSampling
Version: 0.0.2
Summary: Dataset size reduction using KNN Sampling algorithm
Home-page: https://github.com/snimale/KNNSampler
Author: Soham S. Nimale
Author-email: soham.sachin.nimale@gmail.com
License: MIT
Keywords: python,K-NN,Sampling,Size reduction,Optimization,knn sampler
Classifier: License :: OSI Approved :: MIT License
Classifier: Programming Language :: Python :: 3.10
Classifier: Operating System :: OS Independent
License-File: LICENSE
Requires-Dist: numpy
Requires-Dist: pandas
Requires-Dist: scikit-learn
